MemoLib/__init__.py
MemoLib/DataSerializer/ConfigClasses.py
MemoLib/DataSerializer/__init__.py
MemoLib/DatasetFormatConvert/Yolo2Classify.py
MemoLib/DatasetFormatConvert/__init__.py
MemoLib/Loss/FocalLoss.py
MemoLib/Loss/__init__.py
MemoLib/Model/IModel.py
MemoLib/Model/MemoModel.py
MemoLib/Model/MemoResult.py
MemoLib/Model/__init__.py
MemoLib/Model/eModel.py
MemoLib/Model/Data/ModelConfig.py
MemoLib/Model/Data/__init__.py
MemoLib/Model/EfficientNet/EfficientNetModel.py
MemoLib/Model/EfficientNet/__init__.py
MemoLib/Model/EfficientNet/utils.py
MemoLib/Model/YOLO/YOLO_Model.py
MemoLib/Model/YOLO/__init__.py
MemoLib/Model/YOLO/utils.py
memolib-0.1.7.9.dist-info/licenses/LICENSE
memolib-0.1.7.9.dist-info/METADATA
memolib-0.1.7.9.dist-info/WHEEL
memolib-0.1.7.9.dist-info/top_level.txt
memolib-0.1.7.9.dist-info/RECORD
