Metadata-Version: 2.4
Name: MemoLib
Version: 0.1.7.9
Summary: A Python library for machine learning model training and inference
Author-email: NghiaPham <nghiaphamkthp2401@gmail.com>
Maintainer-email: NghiaPham <nghiaphamkthp2401@gmail.com>
License: MIT
Project-URL: Homepage, https://github.com/NghiaKTHP/MemoLib
Project-URL: Repository, https://github.com/NghiaKTHP/MemoLib
Project-URL: Documentation, https://github.com/NghiaKTHP/MemoLib#readme
Project-URL: Bug Tracker, https://github.com/NghiaKTHP/MemoLib/issues
Keywords: machine learning,deep learning,pytorch,yolo,efficientnet
Classifier: Development Status :: 3 - Alpha
Classifier: Intended Audience :: Developers
Classifier: Intended Audience :: Science/Research
Classifier: License :: OSI Approved :: MIT License
Classifier: Programming Language :: Python :: 3
Classifier: Programming Language :: Python :: 3.8
Classifier: Programming Language :: Python :: 3.9
Classifier: Programming Language :: Python :: 3.10
Classifier: Programming Language :: Python :: 3.11
Classifier: Topic :: Scientific/Engineering :: Artificial Intelligence
Classifier: Topic :: Software Development :: Libraries :: Python Modules
Requires-Python: >=3.8
License-File: LICENSE
Requires-Dist: torch>=1.12.0
Requires-Dist: torchvision>=0.13.0
Requires-Dist: numpy>=1.21.0
Requires-Dist: opencv-python>=4.5.0
Requires-Dist: pillow>=8.0.0
Requires-Dist: ultralytics>=8.0.0
Requires-Dist: efficientnet-pytorch>=0.7.0
Provides-Extra: dev
Requires-Dist: pytest>=6.0; extra == "dev"
Requires-Dist: black>=22.0; extra == "dev"
Requires-Dist: flake8>=4.0; extra == "dev"
Requires-Dist: mypy>=0.900; extra == "dev"
Provides-Extra: openvino
Requires-Dist: openvino>=2023.0.0; extra == "openvino"
Provides-Extra: all
Requires-Dist: openvino>=2023.0.0; extra == "all"
Dynamic: license-file
